pytest_verbose_parametrize.py
pytest_verbose_parametrize-1.8.1.dist-info/LICENSE
pytest_verbose_parametrize-1.8.1.dist-info/METADATA
pytest_verbose_parametrize-1.8.1.dist-info/WHEEL
pytest_verbose_parametrize-1.8.1.dist-info/entry_points.txt
pytest_verbose_parametrize-1.8.1.dist-info/top_level.txt
pytest_verbose_parametrize-1.8.1.dist-info/RECORD
